{
  "date": "2017.Dec.12",
  "episodes": "22 bits from ep.524",
  "report": [
    {
      "episode": 524,
      "image": "http://farm5.staticflickr.com/4565/38135424315_1b96f4809c_b.jpg",
      "raw_bits": [
        "The Paul Hardcastle of Suicides",
        "The Paul Hardcastle of Suicides",
        "The Paul Hardcastle of Suicides",
        "The Paul Hardcastle of Suicides",
        "The Paul Hardcastle of Suicides",
        "The Paul Hardcastle of Suicides",
        "The Paul Hardcastle of Suicides",
        "Scott's Questions",
        "Scott's Questions",
        "Scott's Questions",
        "Location",
        "Location",
        "Location",
        "Location",
        "Fantastic.",
        "Favorite Feature",
        "Oh Boy",
        "Oh Boy",
        "What's This, Now?!",
        "Willfully Obtuse"
      ],
      "bits_sum": [
        {
          "bit": "The Paul Hardcastle of Suicides",
          "count": 7
        },
        {
          "bit": "Scott's Questions",
          "count": 3
        },
        {
          "bit": "Location",
          "count": 4
        },
        {
          "bit": "Fantastic.",
          "count": 1
        },
        {
          "bit": "Favorite Feature",
          "count": 1
        },
        {
          "bit": "Oh Boy",
          "count": 2
        },
        {
          "bit": "What's This, Now?!",
          "count": 1
        },
        {
          "bit": "Willfully Obtuse",
          "count": 1
        }
      ]
    }
  ]
}