[{
    "episode": 261,
    "show": "cbb",
    "tstart": "2:52",
    "tend": "2:58",
    "instance": "Directly across from me, in my opinion.",
    "bit":"12 o'Clock","elucidation":"someone (usually scott), belabors the layout and organization of the room",
    "location_type": "",
    "location_id": "",
    "updated_at": "2017-03-15T10:38:33Z",
    "url_soundcloud": "http://soundcloud.com/comedybangbang/261-horatio-sanz-kulap/#t=2:52",
    "tags": "",
    "created_at": "2017-03-15T10:38:33Z",
    "slug_soundcloud": "261-horatio-sanz-kulap",
    "slug_earwolf": "nubile-agape",
    "episode_title": "Nubile Agape",
    "episode_guests": "Horatio Sanz,Kulap Vilaysack,Shelby Fero",
    "id_wikia": 3949,
    "holding": "false"
},

{
    "episode": 261,
    "show": "cbb",
    "tstart": "3:23",
    "tend": "3:34",
    "instance": "There's no 'Y' in the name.",
    "bit":"What's This, Now?!","elucidation":"something surprises someone",
    "location_type": "",
    "location_id": "",
    "updated_at": "2017-03-15T10:38:33Z",
    "url_soundcloud": "http://soundcloud.com/comedybangbang/261-horatio-sanz-kulap/#t=3:23",
    "tags": "",
    "created_at": "2017-03-15T10:38:33Z",
    "slug_soundcloud": "261-horatio-sanz-kulap",
    "slug_earwolf": "nubile-agape",
    "episode_title": "Nubile Agape",
    "episode_guests": "Horatio Sanz,Kulap Vilaysack,Shelby Fero",
    "id_wikia": 3949,
    "holding": "false"
},

{
    "episode": 261,
    "show": "cbb",
    "tstart": "9:03",
    "tend": "10:04",
    "instance": "We did twists on old classics.",
    "bit":"The Paul Hardcastle of Suicides","elucidation":"any song reference",
    "location_type": "",
    "location_id": "",
    "updated_at": "2017-03-15T10:38:33Z",
    "url_soundcloud": "http://soundcloud.com/comedybangbang/261-horatio-sanz-kulap/#t=9:03",
    "tags": "Chubby Checker,The Fat Boys (musical combination),The Twist (song),Bruce Springsteen",
    "created_at": "2017-03-15T10:38:33Z",
    "slug_soundcloud": "261-horatio-sanz-kulap",
    "slug_earwolf": "nubile-agape",
    "episode_title": "Nubile Agape",
    "episode_guests": "Horatio Sanz,Kulap Vilaysack,Shelby Fero",
    "id_wikia": 3949,
    "holding": "false"
},

{
    "episode": 261,
    "show": "cbb",
    "tstart": "12:50",
    "tend": "13:12",
    "instance": "I didn't know that was an original.",
    "bit":"The Paul Hardcastle of Suicides","elucidation":"any song reference",
    "location_type": "",
    "location_id": "",
    "updated_at": "2017-03-15T10:38:33Z",
    "url_soundcloud": "http://soundcloud.com/comedybangbang/261-horatio-sanz-kulap/#t=12:50",
    "tags": "All I Want for Christmas Is You (song),Mariah Carey",
    "created_at": "2017-03-15T10:38:33Z",
    "slug_soundcloud": "261-horatio-sanz-kulap",
    "slug_earwolf": "nubile-agape",
    "episode_title": "Nubile Agape",
    "episode_guests": "Horatio Sanz,Kulap Vilaysack,Shelby Fero",
    "id_wikia": 3949,
    "holding": "false"
},

{
    "episode": 261,
    "show": "cbb",
    "tstart": "16:43",
    "tend": "16:54",
    "instance": "I imagine you going back to school and finding out about, like, commas.",
    "bit":"The Paul Hardcastle of Suicides","elucidation":"any song reference",
    "location_type": "",
    "location_id": "",
    "updated_at": "2017-03-15T10:38:33Z",
    "url_soundcloud": "http://soundcloud.com/comedybangbang/261-horatio-sanz-kulap/#t=16:43",
    "tags": "Oxford Comma (song),Vampire Weekend (musical combination)",
    "created_at": "2017-03-15T10:38:33Z",
    "slug_soundcloud": "261-horatio-sanz-kulap",
    "slug_earwolf": "nubile-agape",
    "episode_title": "Nubile Agape",
    "episode_guests": "Horatio Sanz,Kulap Vilaysack,Shelby Fero",
    "id_wikia": 3949,
    "holding": "false"
},

{
    "episode": 261,
    "show": "cbb",
    "tstart": "18:12",
    "tend": "18:19",
    "instance": "I don't get it.",
    "bit":"Maybe It's Just Me, But for Me","elucidation":"scott has opinions",
    "location_type": "",
    "location_id": "",
    "updated_at": "2017-03-15T10:38:33Z",
    "url_soundcloud": "http://soundcloud.com/comedybangbang/261-horatio-sanz-kulap/#t=18:12",
    "tags": "Citizen Kane (film),The Godfather (film)",
    "created_at": "2017-03-15T10:38:33Z",
    "slug_soundcloud": "261-horatio-sanz-kulap",
    "slug_earwolf": "nubile-agape",
    "episode_title": "Nubile Agape",
    "episode_guests": "Horatio Sanz,Kulap Vilaysack,Shelby Fero",
    "id_wikia": 3949,
    "holding": "false"
},

{
    "episode": 261,
    "show": "cbb",
    "tstart": "37:23",
    "tend": "37:39",
    "instance": "By the way, what are the greatest hits of The Neville Brothers?",
    "bit":"The Paul Hardcastle of Suicides","elucidation":"any song reference",
    "location_type": "",
    "location_id": "",
    "updated_at": "2017-03-15T10:38:33Z",
    "url_soundcloud": "http://soundcloud.com/comedybangbang/261-horatio-sanz-kulap/#t=37:23",
    "tags": "Tell it Like it Is (song),Aaron Neville",
    "created_at": "2017-03-15T10:38:33Z",
    "slug_soundcloud": "261-horatio-sanz-kulap",
    "slug_earwolf": "nubile-agape",
    "episode_title": "Nubile Agape",
    "episode_guests": "Horatio Sanz,Kulap Vilaysack,Shelby Fero",
    "id_wikia": 3949,
    "holding": "false"
},

{
    "episode": 261,
    "show": "cbb",
    "tstart": "37:23",
    "tend": "37:52",
    "instance": "Oh now I know who he is.",
    "bit":"The Paul Hardcastle of Suicides","elucidation":"any song reference",
    "location_type": "",
    "location_id": "",
    "updated_at": "2017-03-15T10:38:33Z",
    "url_soundcloud": "http://soundcloud.com/comedybangbang/261-horatio-sanz-kulap/#t=37:23",
    "tags": "Don't Know Much (song),Linda Ronstadt,Aaron Neville",
    "created_at": "2017-03-15T10:38:33Z",
    "slug_soundcloud": "261-horatio-sanz-kulap",
    "slug_earwolf": "nubile-agape",
    "episode_title": "Nubile Agape",
    "episode_guests": "Horatio Sanz,Kulap Vilaysack,Shelby Fero",
    "id_wikia": 3949,
    "holding": "false"
},

{
    "episode": 261,
    "show": "cbb",
    "tstart": "1:10:24",
    "tend": "1:11:19",
    "instance": "Women fought for your right to be lunkheads in the 70s.",
    "bit":"The Paul Hardcastle of Suicides","elucidation":"any song reference",
    "location_type": "",
    "location_id": "",
    "updated_at": "2017-03-15T10:38:33Z",
    "url_soundcloud": "http://soundcloud.com/comedybangbang/261-horatio-sanz-kulap/#t=1:10:24",
    "tags": "Suffragette City (song),Aaron Neville,David Bowie",
    "created_at": "2017-03-15T10:38:33Z",
    "slug_soundcloud": "261-horatio-sanz-kulap",
    "slug_earwolf": "nubile-agape",
    "episode_title": "Nubile Agape",
    "episode_guests": "Horatio Sanz,Kulap Vilaysack,Shelby Fero",
    "id_wikia": 3949,
    "holding": "false"
},

{
    "episode": 262,
    "show": "cbb",
    "tstart": "1:41",
    "tend": "1:52",
    "instance": "Sometimes I like to reiterate.",
    "bit":"You're Terrible at This","elucidation":"impromptu reviews of scott's hosting",
    "location_type": "",
    "location_id": "",
    "updated_at": "2017-03-15T13:57:42Z",
    "url_soundcloud": "http://soundcloud.com/comedybangbang/2013-holiday-spectacular/#t=1:41",
    "tags": "",
    "created_at": "2017-03-15T13:57:42Z",
    "slug_soundcloud": "2013-holiday-spectacular",
    "slug_earwolf": "2013-holiday-spectacular",
    "episode_title": "2013 Holiday Spectacular",
    "episode_guests": "Nick Lowe,Jason Mantzoukas,Andy Daly,Paul F. Tompkins,James Adomian,Jon Daly,Neil Campbell,Paul Rust,Paul Scheer",
    "id_wikia": 3986,
    "holding": "false"
},

{
    "episode": 262,
    "show": "cbb",
    "tstart": "15:07",
    "tend": "15:34",
    "instance": "Ooh, I love this question.",
    "bit":"The Paul Hardcastle of Suicides","elucidation":"any song reference",
    "location_type": "",
    "location_id": "",
    "updated_at": "2017-03-15T13:57:42Z",
    "url_soundcloud": "http://soundcloud.com/comedybangbang/2013-holiday-spectacular/#t=15:07",
    "tags": "It's Christmas Time in Louisiana (song),Johnnie Allan",
    "created_at": "2017-03-15T13:57:42Z",
    "slug_soundcloud": "2013-holiday-spectacular",
    "slug_earwolf": "2013-holiday-spectacular",
    "episode_title": "2013 Holiday Spectacular",
    "episode_guests": "Nick Lowe,Jason Mantzoukas,Andy Daly,Paul F. Tompkins,James Adomian,Jon Daly,Neil Campbell,Paul Rust,Paul Scheer",
    "id_wikia": 3986,
    "holding": "false"
},

{
    "episode": 262,
    "show": "cbb",
    "tstart": "15:07",
    "tend": "15:34",
    "instance": "Ooh, I love this question.",
    "bit":"The Paul Hardcastle of Suicides","elucidation":"any song reference",
    "location_type": "",
    "location_id": "",
    "updated_at": "2017-03-15T13:57:42Z",
    "url_soundcloud": "http://soundcloud.com/comedybangbang/2013-holiday-spectacular/#t=15:07",
    "tags": "Bling Bling Christmas (song),The Silvertones (musical combination)",
    "created_at": "2017-03-15T13:57:42Z",
    "slug_soundcloud": "2013-holiday-spectacular",
    "slug_earwolf": "2013-holiday-spectacular",
    "episode_title": "2013 Holiday Spectacular",
    "episode_guests": "Nick Lowe,Jason Mantzoukas,Andy Daly,Paul F. Tompkins,James Adomian,Jon Daly,Neil Campbell,Paul Rust,Paul Scheer",
    "id_wikia": 3986,
    "holding": "false"
},

{
    "episode": 262,
    "show": "cbb",
    "tstart": "15:07",
    "tend": "15:34",
    "instance": "Ooh, I love this question.",
    "bit":"The Paul Hardcastle of Suicides","elucidation":"any song reference",
    "location_type": "",
    "location_id": "",
    "updated_at": "2017-03-15T13:57:42Z",
    "url_soundcloud": "http://soundcloud.com/comedybangbang/2013-holiday-spectacular/#t=15:07",
    "tags": "A New Baby for Christmas (song),George Jones",
    "created_at": "2017-03-15T13:57:42Z",
    "slug_soundcloud": "2013-holiday-spectacular",
    "slug_earwolf": "2013-holiday-spectacular",
    "episode_title": "2013 Holiday Spectacular",
    "episode_guests": "Nick Lowe,Jason Mantzoukas,Andy Daly,Paul F. Tompkins,James Adomian,Jon Daly,Neil Campbell,Paul Rust,Paul Scheer",
    "id_wikia": 3986,
    "holding": "false"
},

{
    "episode": 262,
    "show": "cbb",
    "tstart": "15:30",
    "tend": "15:37",
    "instance": "Do you like those singing Jingle Bells dogs?",
    "bit":"Scott's Questions","elucidation":"(in progress) - scott's questions",
    "location_type": "",
    "location_id": "",
    "updated_at": "2017-03-15T13:57:42Z",
    "url_soundcloud": "http://soundcloud.com/comedybangbang/2013-holiday-spectacular/#t=15:30",
    "tags": "A New Baby for Christmas (song),George Jones",
    "created_at": "2017-03-15T13:57:42Z",
    "slug_soundcloud": "2013-holiday-spectacular",
    "slug_earwolf": "2013-holiday-spectacular",
    "episode_title": "2013 Holiday Spectacular",
    "episode_guests": "Nick Lowe,Jason Mantzoukas,Andy Daly,Paul F. Tompkins,James Adomian,Jon Daly,Neil Campbell,Paul Rust,Paul Scheer",
    "id_wikia": 3986,
    "holding": "false"
},

{
    "episode": 262,
    "show": "cbb",
    "tstart": "15:30",
    "tend": "15:37",
    "instance": "Do you like those singing Jingle Bells dogs?",
    "bit":"The Paul Hardcastle of Suicides","elucidation":"any song reference",
    "location_type": "",
    "location_id": "",
    "updated_at": "2017-03-15T13:57:42Z",
    "url_soundcloud": "http://soundcloud.com/comedybangbang/2013-holiday-spectacular/#t=15:30",
    "tags": "Jingle Bells (song),The Singing Dogs (musical combination),James Lord Pierpont",
    "created_at": "2017-03-15T13:57:42Z",
    "slug_soundcloud": "2013-holiday-spectacular",
    "slug_earwolf": "2013-holiday-spectacular",
    "episode_title": "2013 Holiday Spectacular",
    "episode_guests": "Nick Lowe,Jason Mantzoukas,Andy Daly,Paul F. Tompkins,James Adomian,Jon Daly,Neil Campbell,Paul Rust,Paul Scheer",
    "id_wikia": 3986,
    "holding": "false"
},

{
    "episode": 262,
    "show": "cbb",
    "tstart": "18:50",
    "tend": "19:03",
    "instance": "The last song that sort of joined the canon...",
    "bit":"The Paul Hardcastle of Suicides","elucidation":"any song reference",
    "location_type": "",
    "location_id": "",
    "updated_at": "2017-03-15T13:57:42Z",
    "url_soundcloud": "http://soundcloud.com/comedybangbang/2013-holiday-spectacular/#t=18:50",
    "tags": "Fairy Tale of New York (song),The Pogues (musical combination),Kirsty MacColl",
    "created_at": "2017-03-15T13:57:42Z",
    "slug_soundcloud": "2013-holiday-spectacular",
    "slug_earwolf": "2013-holiday-spectacular",
    "episode_title": "2013 Holiday Spectacular",
    "episode_guests": "Nick Lowe,Jason Mantzoukas,Andy Daly,Paul F. Tompkins,James Adomian,Jon Daly,Neil Campbell,Paul Rust,Paul Scheer",
    "id_wikia": 3986,
    "holding": "false"
},

{
    "episode": 262,
    "show": "cbb",
    "tstart": "19:03",
    "tend": "19:13",
    "instance": "It's hard to think of one since then.",
    "bit":"The Paul Hardcastle of Suicides","elucidation":"any song reference",
    "location_type": "",
    "location_id": "",
    "updated_at": "2017-03-15T13:57:42Z",
    "url_soundcloud": "http://soundcloud.com/comedybangbang/2013-holiday-spectacular/#t=19:03",
    "tags": "Last Christmas (song),Wham! (musical combination)",
    "created_at": "2017-03-15T13:57:42Z",
    "slug_soundcloud": "2013-holiday-spectacular",
    "slug_earwolf": "2013-holiday-spectacular",
    "episode_title": "2013 Holiday Spectacular",
    "episode_guests": "Nick Lowe,Jason Mantzoukas,Andy Daly,Paul F. Tompkins,James Adomian,Jon Daly,Neil Campbell,Paul Rust,Paul Scheer",
    "id_wikia": 3986,
    "holding": "false"
},

{
    "episode": 262,
    "show": "cbb",
    "tstart": "19:10",
    "tend": "19:28",
    "instance": "That predated it.",
    "bit":"The Paul Hardcastle of Suicides","elucidation":"any song reference",
    "location_type": "",
    "location_id": "",
    "updated_at": "2017-03-15T13:57:42Z",
    "url_soundcloud": "http://soundcloud.com/comedybangbang/2013-holiday-spectacular/#t=19:10",
    "tags": "All I Want for Christmas is You (song),Mariah Carey",
    "created_at": "2017-03-15T13:57:42Z",
    "slug_soundcloud": "2013-holiday-spectacular",
    "slug_earwolf": "2013-holiday-spectacular",
    "episode_title": "2013 Holiday Spectacular",
    "episode_guests": "Nick Lowe,Jason Mantzoukas,Andy Daly,Paul F. Tompkins,James Adomian,Jon Daly,Neil Campbell,Paul Rust,Paul Scheer",
    "id_wikia": 3986,
    "holding": "false"
},

{
    "episode": 262,
    "show": "cbb",
    "tstart": "39:27",
    "tend": "39:36",
    "instance": "You don't drive a Jeep, do you Dalton?",
    "bit":"Location","elucidation":"identifiable earth location",
    "location_type": "line",
    "location_id": "123",
    "updated_at": "2017-03-15T13:57:42Z",
    "url_soundcloud": "http://soundcloud.com/comedybangbang/2013-holiday-spectacular/#t=39:27",
    "tags": "Dalton Wilcox",
    "created_at": "2017-03-15T13:57:42Z",
    "slug_soundcloud": "2013-holiday-spectacular",
    "slug_earwolf": "2013-holiday-spectacular",
    "episode_title": "2013 Holiday Spectacular",
    "episode_guests": "Nick Lowe,Jason Mantzoukas,Andy Daly,Paul F. Tompkins,James Adomian,Jon Daly,Neil Campbell,Paul Rust,Paul Scheer",
    "id_wikia": 3986,
    "holding": "false"
},

{
    "episode": 262,
    "show": "cbb",
    "tstart": "44:07",
    "tend": "44:15",
    "instance": "I don't think she has a problem with it because she doesn't know about it.",
    "bit":"Oh Boy","elucidation":"something is disgusting in some way",
    "location_type": "",
    "location_id": "",
    "updated_at": "2017-03-15T13:57:42Z",
    "url_soundcloud": "http://soundcloud.com/comedybangbang/2013-holiday-spectacular/#t=44:07",
    "tags": "Dalton Wilcox",
    "created_at": "2017-03-15T13:57:42Z",
    "slug_soundcloud": "2013-holiday-spectacular",
    "slug_earwolf": "2013-holiday-spectacular",
    "episode_title": "2013 Holiday Spectacular",
    "episode_guests": "Nick Lowe,Jason Mantzoukas,Andy Daly,Paul F. Tompkins,James Adomian,Jon Daly,Neil Campbell,Paul Rust,Paul Scheer",
    "id_wikia": 3986,
    "holding": "false"
},

{
    "episode": 262,
    "show": "cbb",
    "tstart": "47:09",
    "tend": "47:20",
    "instance": "Did you ever see Joanna Kerns naked?",
    "bit":"Scott's Questions","elucidation":"(in progress) - scott's questions",
    "location_type": "",
    "location_id": "",
    "updated_at": "2017-03-15T13:57:42Z",
    "url_soundcloud": "http://soundcloud.com/comedybangbang/2013-holiday-spectacular/#t=47:09",
    "tags": "Joanna Kerns,Alan Thicke",
    "created_at": "2017-03-15T13:57:42Z",
    "slug_soundcloud": "2013-holiday-spectacular",
    "slug_earwolf": "2013-holiday-spectacular",
    "episode_title": "2013 Holiday Spectacular",
    "episode_guests": "Nick Lowe,Jason Mantzoukas,Andy Daly,Paul F. Tompkins,James Adomian,Jon Daly,Neil Campbell,Paul Rust,Paul Scheer",
    "id_wikia": 3986,
    "holding": "false"
},

{
    "episode": 262,
    "show": "cbb",
    "tstart": "47:50",
    "tend": "47:59",
    "instance": "Did you ever have sex with any of those Designing Women?",
    "bit":"Scott's Questions","elucidation":"(in progress) - scott's questions",
    "location_type": "",
    "location_id": "",
    "updated_at": "2017-03-15T13:57:42Z",
    "url_soundcloud": "http://soundcloud.com/comedybangbang/2013-holiday-spectacular/#t=47:50",
    "tags": "Designing Women (TV),Alan Thicke",
    "created_at": "2017-03-15T13:57:42Z",
    "slug_soundcloud": "2013-holiday-spectacular",
    "slug_earwolf": "2013-holiday-spectacular",
    "episode_title": "2013 Holiday Spectacular",
    "episode_guests": "Nick Lowe,Jason Mantzoukas,Andy Daly,Paul F. Tompkins,James Adomian,Jon Daly,Neil Campbell,Paul Rust,Paul Scheer",
    "id_wikia": 3986,
    "holding": "false"
},

{
    "episode": 262,
    "show": "cbb",
    "tstart": "50:30",
    "tend": "52:19",
    "instance": "Well, sure, because it's the opposite side of the world.",
    "bit":"The Paul Hardcastle of Suicides","elucidation":"any song reference",
    "location_type": "",
    "location_id": "",
    "updated_at": "2017-03-15T13:57:42Z",
    "url_soundcloud": "http://soundcloud.com/comedybangbang/2013-holiday-spectacular/#t=50:30",
    "tags": "Wipe Out (song),The Surfaris (musical combination),Alan Thicke",
    "created_at": "2017-03-15T13:57:42Z",
    "slug_soundcloud": "2013-holiday-spectacular",
    "slug_earwolf": "2013-holiday-spectacular",
    "episode_title": "2013 Holiday Spectacular",
    "episode_guests": "Nick Lowe,Jason Mantzoukas,Andy Daly,Paul F. Tompkins,James Adomian,Jon Daly,Neil Campbell,Paul Rust,Paul Scheer",
    "id_wikia": 3986,
    "holding": "false"
},

{
    "episode": 262,
    "show": "cbb",
    "tstart": "52:01",
    "tend": "52:19",
    "instance": "Those are lyrics that are in but are frequently not sung.",
    "bit":"The Paul Hardcastle of Suicides","elucidation":"any song reference",
    "location_type": "",
    "location_id": "",
    "updated_at": "2017-03-15T13:57:42Z",
    "url_soundcloud": "http://soundcloud.com/comedybangbang/2013-holiday-spectacular/#t=52:01",
    "tags": "Song from M*A*S*H (Suicide Is Painless) (song),Johnny Mandel,Mike Altman,Alan Thicke",
    "created_at": "2017-03-15T13:57:42Z",
    "slug_soundcloud": "2013-holiday-spectacular",
    "slug_earwolf": "2013-holiday-spectacular",
    "episode_title": "2013 Holiday Spectacular",
    "episode_guests": "Nick Lowe,Jason Mantzoukas,Andy Daly,Paul F. Tompkins,James Adomian,Jon Daly,Neil Campbell,Paul Rust,Paul Scheer",
    "id_wikia": 3986,
    "holding": "false"
},

{
    "episode": 262,
    "show": "cbb",
    "tstart": "53:50",
    "tend": "55:37",
    "instance": "There's a huge time jump in that.",
    "bit":"The Paul Hardcastle of Suicides","elucidation":"any song reference",
    "location_type": "",
    "location_id": "",
    "updated_at": "2017-03-15T13:57:42Z",
    "url_soundcloud": "http://soundcloud.com/comedybangbang/2013-holiday-spectacular/#t=53:50",
    "tags": "It Takes Diff'rent Strokes (song),Alan Thicke,Diff'rent Strokes (TV)",
    "created_at": "2017-03-15T13:57:42Z",
    "slug_soundcloud": "2013-holiday-spectacular",
    "slug_earwolf": "2013-holiday-spectacular",
    "episode_title": "2013 Holiday Spectacular",
    "episode_guests": "Nick Lowe,Jason Mantzoukas,Andy Daly,Paul F. Tompkins,James Adomian,Jon Daly,Neil Campbell,Paul Rust,Paul Scheer",
    "id_wikia": 3986,
    "holding": "false"
},

{
    "episode": 262,
    "show": "cbb",
    "tstart": "1:08:10",
    "tend": "1:08:15",
    "instance": "Someone's here.",
    "bit":"Oh Boy","elucidation":"something is disgusting in some way",
    "location_type": "",
    "location_id": "",
    "updated_at": "2017-03-15T13:57:42Z",
    "url_soundcloud": "http://soundcloud.com/comedybangbang/2013-holiday-spectacular/#t=1:08:10",
    "tags": "Merrill Shindler,Alan Thicke",
    "created_at": "2017-03-15T13:57:42Z",
    "slug_soundcloud": "2013-holiday-spectacular",
    "slug_earwolf": "2013-holiday-spectacular",
    "episode_title": "2013 Holiday Spectacular",
    "episode_guests": "Nick Lowe,Jason Mantzoukas,Andy Daly,Paul F. Tompkins,James Adomian,Jon Daly,Neil Campbell,Paul Rust,Paul Scheer",
    "id_wikia": 3986,
    "holding": "false"
},

{
    "episode": 262,
    "show": "cbb",
    "tstart": "1:15:05",
    "tend": "1:15:24",
    "instance": "Did you write the theme song to 'Its a Living'?",
    "bit":"The Paul Hardcastle of Suicides","elucidation":"any song reference",
    "location_type": "",
    "location_id": "",
    "updated_at": "2017-03-15T13:57:42Z",
    "url_soundcloud": "http://soundcloud.com/comedybangbang/2013-holiday-spectacular/#t=1:15:05",
    "tags": "Merrill Shindler,Alan Thicke,It's a Living (TV),It's a Living (song),Leslie Bricusse",
    "created_at": "2017-03-15T13:57:42Z",
    "slug_soundcloud": "2013-holiday-spectacular",
    "slug_earwolf": "2013-holiday-spectacular",
    "episode_title": "2013 Holiday Spectacular",
    "episode_guests": "Nick Lowe,Jason Mantzoukas,Andy Daly,Paul F. Tompkins,James Adomian,Jon Daly,Neil Campbell,Paul Rust,Paul Scheer",
    "id_wikia": 3986,
    "holding": "false"
},

{
    "episode": 262,
    "show": "cbb",
    "tstart": "1:30:00",
    "tend": "1:30:29",
    "instance": "You both write theme songs.",
    "bit":"The Paul Hardcastle of Suicides","elucidation":"any song reference",
    "location_type": "",
    "location_id": "",
    "updated_at": "2017-03-15T13:57:42Z",
    "url_soundcloud": "http://soundcloud.com/comedybangbang/2013-holiday-spectacular/#t=1:30:00",
    "tags": "Alan Thicke,Far From Over (song),Staying Alive (film),Frank Stallone",
    "created_at": "2017-03-15T13:57:42Z",
    "slug_soundcloud": "2013-holiday-spectacular",
    "slug_earwolf": "2013-holiday-spectacular",
    "episode_title": "2013 Holiday Spectacular",
    "episode_guests": "Nick Lowe,Jason Mantzoukas,Andy Daly,Paul F. Tompkins,James Adomian,Jon Daly,Neil Campbell,Paul Rust,Paul Scheer",
    "id_wikia": 3986,
    "holding": "false"
},

{
    "episode": 262,
    "show": "cbb",
    "tstart": "1:30:34",
    "tend": "1:30:45",
    "instance": "I'm gonna stop you right there, Frank.",
    "bit":"The Paul Hardcastle of Suicides","elucidation":"any song reference",
    "location_type": "",
    "location_id": "",
    "updated_at": "2017-03-15T13:57:42Z",
    "url_soundcloud": "http://soundcloud.com/comedybangbang/2013-holiday-spectacular/#t=1:30:34",
    "tags": "Alan Thicke,Theme from Magnum P.I. (song),Mike Post,Frank Stallone",
    "created_at": "2017-03-15T13:57:42Z",
    "slug_soundcloud": "2013-holiday-spectacular",
    "slug_earwolf": "2013-holiday-spectacular",
    "episode_title": "2013 Holiday Spectacular",
    "episode_guests": "Nick Lowe,Jason Mantzoukas,Andy Daly,Paul F. Tompkins,James Adomian,Jon Daly,Neil Campbell,Paul Rust,Paul Scheer",
    "id_wikia": 3986,
    "holding": "false"
},

{
    "episode": 262,
    "show": "cbb",
    "tstart": "1:30:52",
    "tend": "1:31:03",
    "instance": "When I saw the movie I said I needed to write a song about it.",
    "bit":"The Paul Hardcastle of Suicides","elucidation":"any song reference",
    "location_type": "",
    "location_id": "",
    "updated_at": "2017-03-15T13:57:42Z",
    "url_soundcloud": "http://soundcloud.com/comedybangbang/2013-holiday-spectacular/#t=1:30:52",
    "tags": "Heartlight (song),Frank Stallone,Neil Diamond,Twelve Years a Slave (film),E.T. The Extra-Terrestrial (film)",
    "created_at": "2017-03-15T13:57:42Z",
    "slug_soundcloud": "2013-holiday-spectacular",
    "slug_earwolf": "2013-holiday-spectacular",
    "episode_title": "2013 Holiday Spectacular",
    "episode_guests": "Nick Lowe,Jason Mantzoukas,Andy Daly,Paul F. Tompkins,James Adomian,Jon Daly,Neil Campbell,Paul Rust,Paul Scheer",
    "id_wikia": 3986,
    "holding": "false"
},

{
    "episode": 262,
    "show": "cbb",
    "tstart": "1:40:20",
    "tend": "1:40:25",
    "instance": "You contain eggs, is that true?!",
    "bit":"Oh Boy","elucidation":"something is disgusting in some way",
    "location_type": "",
    "location_id": "",
    "updated_at": "2017-03-15T13:57:42Z",
    "url_soundcloud": "http://soundcloud.com/comedybangbang/2013-holiday-spectacular/#t=1:40:20",
    "tags": "Merrill Shindler",
    "created_at": "2017-03-15T13:57:42Z",
    "slug_soundcloud": "2013-holiday-spectacular",
    "slug_earwolf": "2013-holiday-spectacular",
    "episode_title": "2013 Holiday Spectacular",
    "episode_guests": "Nick Lowe,Jason Mantzoukas,Andy Daly,Paul F. Tompkins,James Adomian,Jon Daly,Neil Campbell,Paul Rust,Paul Scheer",
    "id_wikia": 3986,
    "holding": "false"
},

{
    "episode": 262,
    "show": "cbb",
    "tstart": "1:49:53",
    "tend": "1:50:05",
    "instance": "Have you ever starved almost to death?",
    "bit":"Scott's Questions","elucidation":"(in progress) - scott's questions",
    "location_type": "",
    "location_id": "",
    "updated_at": "2017-03-15T13:57:42Z",
    "url_soundcloud": "http://soundcloud.com/comedybangbang/2013-holiday-spectacular/#t=1:49:53",
    "tags": "Merrill Shindler,Frank Stallone,Alan Thicke",
    "created_at": "2017-03-15T13:57:42Z",
    "slug_soundcloud": "2013-holiday-spectacular",
    "slug_earwolf": "2013-holiday-spectacular",
    "episode_title": "2013 Holiday Spectacular",
    "episode_guests": "Nick Lowe,Jason Mantzoukas,Andy Daly,Paul F. Tompkins,James Adomian,Jon Daly,Neil Campbell,Paul Rust,Paul Scheer",
    "id_wikia": 3986,
    "holding": "false"
},

{
    "episode": 262,
    "show": "cbb",
    "tstart": "2:08:09",
    "tend": "2:08:22",
    "instance": "There's at least a load of my cum in every box.",
    "bit":"Oh Boy","elucidation":"something is disgusting in some way",
    "location_type": "",
    "location_id": "",
    "updated_at": "2017-03-15T13:57:42Z",
    "url_soundcloud": "http://soundcloud.com/comedybangbang/2013-holiday-spectacular/#t=2:08:09",
    "tags": "Alan Thicke,Bill Cosby Bukowski",
    "created_at": "2017-03-15T13:57:42Z",
    "slug_soundcloud": "2013-holiday-spectacular",
    "slug_earwolf": "2013-holiday-spectacular",
    "episode_title": "2013 Holiday Spectacular",
    "episode_guests": "Nick Lowe,Jason Mantzoukas,Andy Daly,Paul F. Tompkins,James Adomian,Jon Daly,Neil Campbell,Paul Rust,Paul Scheer",
    "id_wikia": 3986,
    "holding": "false"
},

{
    "episode": 262,
    "show": "cbb",
    "tstart": "2:10:05",
    "tend": "2:10:20",
    "instance": "We recorded em' today and it's comin' out tomorrow.",
    "bit":"The Paul Hardcastle of Suicides","elucidation":"any song reference",
    "location_type": "",
    "location_id": "",
    "updated_at": "2017-03-16T12:57:42Z",
    "elucidation": "identifiable earth location",
    "url_soundcloud": "http://soundcloud.com/comedybangbang/2013-holiday-spectacular/#t=2:10:05",
    "tags": "Silverchair (musical combination),Tomorrow (song),The Bachelor Brothers, Barrett Bachelor,Benny Bachelor",
    "created_at": "2015-04-03T10:51:29Z",
    "slug_soundcloud": "2013-holiday-spectacular",
    "slug_earwolf": "2013-holiday-spectacular",
    "episode_title": "2013 Holiday Spectacular",
    "episode_guests": "Nick Lowe,Jason Mantzoukas,Andy Daly,Paul F. Tompkins,James Adomian,Jon Daly,Neil Campbell,Paul Rust,Paul Scheer",
    "id_wikia": 3986,
    "holding": "false"
},

{
    "episode": "bo2013.1",
    "show": "cbb",
    "tstart": "5:32",
    "tend": "5:42",
    "instance": "If you want the best --",
    "bit":"The Paul Hardcastle of Suicides","elucidation":"any song reference",
    "location_type": "",
    "location_id": "",
    "updated_at": "2017-03-16T15:18:15Z",
    "url_soundcloud": "http://soundcloud.com/comedybangbang/best-of-2013-pt-1/#t=5:32",
    "tags": "You're the Best (song),Joe Esposito",
    "created_at": "2017-03-16T15:18:15Z",
    "slug_soundcloud": "best-of-2013-pt-1",
    "slug_earwolf": "best-of-2013-pt-1",
    "episode_title": "",
    "episode_guests": "",
    "id_wikia": 4024,
    "holding": "false"
},

{
    "episode": "bo2013.1",
    "show": "cbb",
    "tstart": "5:32",
    "tend": "6:22",
    "instance": "If you want the best --",
    "bit":"The Paul Hardcastle of Suicides","elucidation":"any song reference",
    "location_type": "",
    "location_id": "",
    "updated_at": "2017-03-16T15:18:15Z",
    "url_soundcloud": "http://soundcloud.com/comedybangbang/best-of-2013-pt-1/#t=5:32",
    "tags": "Touch Me (song),The Doors (musical combination)",
    "created_at": "2017-03-16T15:18:15Z",
    "slug_soundcloud": "best-of-2013-pt-1",
    "slug_earwolf": "best-of-2013-pt-1",
    "episode_title": "",
    "episode_guests": "",
    "id_wikia": 4024,
    "holding": "false"
},

{
    "episode": "bo2013.1",
    "show": "cbb",
    "tstart": "7:57",
    "tend": "8:01",
    "instance": "I guess the feeling's right.",
    "bit":"The Paul Hardcastle of Suicides","elucidation":"any song reference",
    "location_type": "",
    "location_id": "",
    "updated_at": "2017-03-16T15:18:15Z",
    "url_soundcloud": "http://soundcloud.com/comedybangbang/best-of-2013-pt-1/#t=7:57",
    "tags": "Ladies' Night (song),Kool & the Gang (musical combination)",
    "created_at": "2017-03-16T15:18:15Z",
    "slug_soundcloud": "best-of-2013-pt-1",
    "slug_earwolf": "best-of-2013-pt-1",
    "episode_title": "",
    "episode_guests": "",
    "id_wikia": 4024,
    "holding": "false"
},

{
    "episode": "bo2013.1",
    "show": "cbb",
    "tstart": "8:25",
    "tend": "8:31",
    "instance": "You know who else comes out at night?",
    "bit":"The Paul Hardcastle of Suicides","elucidation":"any song reference",
    "location_type": "",
    "location_id": "",
    "updated_at": "2017-03-16T15:18:15Z",
    "url_soundcloud": "http://soundcloud.com/comedybangbang/best-of-2013-pt-1/#t=8:25",
    "tags": "Freaks Come out at Night (song),Whodini (musical combination)",
    "created_at": "2017-03-16T15:18:15Z",
    "slug_soundcloud": "best-of-2013-pt-1",
    "slug_earwolf": "best-of-2013-pt-1",
    "episode_title": "",
    "episode_guests": "",
    "id_wikia": 4024,
    "holding": "false"
},

{
    "episode": "bo2013.1",
    "show": "cbb",
    "tstart": "8:33",
    "tend": "8:41",
    "instance": "I hope that a superfreak will defend us against the freaks.",
    "bit":"The Paul Hardcastle of Suicides","elucidation":"any song reference",
    "location_type": "",
    "location_id": "",
    "updated_at": "2017-03-16T15:18:15Z",
    "url_soundcloud": "http://soundcloud.com/comedybangbang/best-of-2013-pt-1/#t=8:33",
    "tags": "Super Freak (song),Rick James",
    "created_at": "2017-03-16T15:18:15Z",
    "slug_soundcloud": "best-of-2013-pt-1",
    "slug_earwolf": "best-of-2013-pt-1",
    "episode_title": "",
    "episode_guests": "",
    "id_wikia": 4024,
    "holding": "false"
},

{
    "episode": "bo2013.1",
    "show": "cbb",
    "tstart": "1:35:50",
    "tend": "1:36:00",
    "instance": "Herman Cain!",
    "bit":"The Paul Hardcastle of Suicides","elucidation":"any song reference",
    "location_type": "",
    "location_id": "",
    "updated_at": "2017-03-16T15:18:15Z",
    "url_soundcloud": "http://soundcloud.com/comedybangbang/best-of-2013-pt-1/#t=1:35:50",
    "tags": "Rock You Like a Hurricane (song),Scorpions (musical combination),Herman Cain",
    "created_at": "2017-03-16T15:18:15Z",
    "slug_soundcloud": "best-of-2013-pt-1",
    "slug_earwolf": "best-of-2013-pt-1",
    "episode_title": "",
    "episode_guests": "",
    "id_wikia": 4024,
    "holding": "false"
},

{
    "episode": "bo2013.2",
    "show": "cbb",
    "tstart": "0:38",
    "tend": "1:05",
    "instance": "I wanna take you to part two.",
    "bit":"The Paul Hardcastle of Suicides","elucidation":"any song reference",
    "location_type": "",
    "location_id": "",
    "updated_at": "2017-03-17T12:01:53Z",
    "url_soundcloud": "http://soundcloud.com/comedybangbang/best-of-2013-pt-2/#t=0:38",
    "tags": "Big Audio Dynamite (musical combination),The Bottom Line (song)",
    "created_at": "2017-03-17T12:01:53Z",
    "slug_soundcloud": "best-of-2013-pt-2",
    "slug_earwolf": "best-of-2013-pt-2",
    "episode_title": "",
    "episode_guests": "",
    "id_wikia": 4032,
    "holding": "false"
},

{
    "episode": "bo2013.2",
    "show": "cbb",
    "tstart": "2:23",
    "tend": "2:57",
    "instance": "And this is how I see you.",
    "bit": "Hello?","elucidation": "the lionel richie videotic atrocity",
    "location_type": "",
    "location_id": "",
    "updated_at": "2017-03-17T12:01:53Z",
    "url_soundcloud": "http://soundcloud.com/comedybangbang/best-of-2013-pt-2/#t=2:23",
    "tags": "Lionel Richie,Hello (song)",
    "created_at": "2017-03-17T12:01:53Z",
    "slug_soundcloud": "best-of-2013-pt-2",
    "slug_earwolf": "best-of-2013-pt-2",
    "episode_title": "",
    "episode_guests": "",
    "id_wikia": 4032,
    "holding": "false"
},

{
    "episode": "bo2013.2",
    "show": "cbb",
    "tstart": "5:33",
    "tend": "6:06",
    "instance": "You're hiding it, though.",
    "bit":"The Paul Hardcastle of Suicides","elucidation":"any song reference",
    "location_type": "",
    "location_id": "",
    "updated_at": "2017-03-17T12:01:53Z",
    "url_soundcloud": "http://soundcloud.com/comedybangbang/best-of-2013-pt-2/#t=5:33",
    "tags": "The Pointer Sisters (musical combination),I'm So Excited (song)",
    "created_at": "2017-03-17T12:01:53Z",
    "slug_soundcloud": "best-of-2013-pt-2",
    "slug_earwolf": "best-of-2013-pt-2",
    "episode_title": "",
    "episode_guests": "",
    "id_wikia": 4032,
    "holding": "false"
},

{
    "episode": "bo2013.2",
    "show": "cbb",
    "tstart": "5:47",
    "tend": "5:58",
    "instance": "Control-wise how are you feeling?",
    "bit":"The Paul Hardcastle of Suicides","elucidation":"any song reference",
    "location_type": "",
    "location_id": "",
    "updated_at": "2017-03-17T12:01:53Z",
    "url_soundcloud": "http://soundcloud.com/comedybangbang/best-of-2013-pt-2/#t=5:47",
    "tags": "Janet Jackson,Control (song)",
    "created_at": "2017-03-17T12:01:53Z",
    "slug_soundcloud": "best-of-2013-pt-2",
    "slug_earwolf": "best-of-2013-pt-2",
    "episode_title": "",
    "episode_guests": "",
    "id_wikia": 4032,
    "holding": "false"
},

{
    "episode": "bo2013.2",
    "show": "cbb",
    "tstart": "38:28",
    "tend": "38:38",
    "instance": "I'm dumb.",
    "bit":"The Paul Hardcastle of Suicides","elucidation":"any song reference",
    "location_type": "",
    "location_id": "",
    "updated_at": "2017-03-17T12:01:53Z",
    "url_soundcloud": "http://soundcloud.com/comedybangbang/best-of-2013-pt-2/#t=38:28",
    "tags": "The Pointer Sisters (musical combination),I'm So Excited (song)",
    "created_at": "2017-03-17T12:01:53Z",
    "slug_soundcloud": "best-of-2013-pt-2",
    "slug_earwolf": "best-of-2013-pt-2",
    "episode_title": "",
    "episode_guests": "",
    "id_wikia": 4032,
    "holding": "false"
},

{
    "episode": "bo2013.2",
    "show": "cbb",
    "tstart": "39:11",
    "tend": "39:48",
    "instance": "Alright, we have time.",
    "bit":"The Paul Hardcastle of Suicides","elucidation":"any song reference",
    "location_type": "",
    "location_id": "",
    "updated_at": "2017-03-17T12:01:53Z",
    "url_soundcloud": "http://soundcloud.com/comedybangbang/best-of-2013-pt-2/#t=39:11",
    "tags": "Jim Croce,Time in a Bottle (song)",
    "created_at": "2017-03-17T12:01:53Z",
    "slug_soundcloud": "best-of-2013-pt-2",
    "slug_earwolf": "best-of-2013-pt-2",
    "episode_title": "",
    "episode_guests": "",
    "id_wikia": 4032,
    "holding": "false"
},

{
    "episode": "bo2013.2",
    "show": "cbb",
    "tstart": "42:36",
    "tend": "42:50",
    "instance": "What's Jason Mantzoukas a person from?",
    "bit":"Jeffrey Characterwheaties","elucidation":"a real sweetheart plays a real dirtbag",
    "location_type": "",
    "location_id": "",
    "updated_at": "2017-03-17T12:01:53Z",
    "url_soundcloud": "http://soundcloud.com/comedybangbang/best-of-2013-pt-2/#t=42:36",
    "tags": "The Bachelor Brothers",
    "created_at": "2017-03-17T12:01:53Z",
    "slug_soundcloud": "best-of-2013-pt-2",
    "slug_earwolf": "best-of-2013-pt-2",
    "episode_title": "",
    "episode_guests": "",
    "id_wikia": 4032,
    "holding": "false"
},

{
    "episode": "bo2013.2",
    "show": "cbb",
    "tstart": "43:06",
    "tend": "43:17",
    "instance": "One is seventeen. The end.",
    "bit":"The Paul Hardcastle of Suicides","elucidation":"any song reference",
    "location_type": "",
    "location_id": "",
    "updated_at": "2017-03-17T12:01:53Z",
    "url_soundcloud": "http://soundcloud.com/comedybangbang/best-of-2013-pt-2/#t=43:06",
    "tags": "Sixteen Going On Seventeen (song),The Sound of Music (musical),Oscar Hammerstein II,Richard Rodgers",
    "created_at": "2017-03-17T12:01:53Z",
    "slug_soundcloud": "best-of-2013-pt-2",
    "slug_earwolf": "best-of-2013-pt-2",
    "episode_title": "",
    "episode_guests": "",
    "id_wikia": 4032,
    "holding": "false"
},

{
    "episode": "bo2013.2",
    "show": "cbb",
    "tstart": "1:08:12",
    "tend": "1:08:35",
    "instance": "He doesn't know the territory.",
    "bit":"The Paul Hardcastle of Suicides","elucidation":"any song reference",
    "location_type": "",
    "location_id": "",
    "updated_at": "2017-03-17T12:01:53Z",
    "url_soundcloud": "http://soundcloud.com/comedybangbang/best-of-2013-pt-2/#t=1:08:12",
    "tags": "Rock Island (song),Music Man (musical),Meredith Willson",
    "created_at": "2017-03-17T12:01:53Z",
    "slug_soundcloud": "best-of-2013-pt-2",
    "slug_earwolf": "best-of-2013-pt-2",
    "episode_title": "",
    "episode_guests": "",
    "id_wikia": 4032,
    "holding": "false"
},

{
    "episode": "bo2013.2",
    "show": "cbb",
    "tstart": "1:33:54",
    "tend": "1:34:21",
    "instance": "I believe the children are...certainly *a* future.",
    "bit":"The Paul Hardcastle of Suicides","elucidation":"any song reference",
    "location_type": "",
    "location_id": "",
    "updated_at": "2017-03-17T12:01:53Z",
    "url_soundcloud": "http://soundcloud.com/comedybangbang/best-of-2013-pt-2/#t=1:33:54",
    "tags": "Greatest Love of All (song),Whitney Houston",
    "created_at": "2017-03-17T12:01:53Z",
    "slug_soundcloud": "best-of-2013-pt-2",
    "slug_earwolf": "best-of-2013-pt-2",
    "episode_title": "",
    "episode_guests": "",
    "id_wikia": 4032,
    "holding": "false"
},

{
    "episode": "bo2013.2",
    "show": "cbb",
    "tstart": "2:00:43",
    "tend": "2:01:01",
    "instance": "It's also on my YouTube channel.",
    "bit":"The Paul Hardcastle of Suicides","elucidation":"any song reference",
    "location_type": "",
    "location_id": "",
    "updated_at": "2017-03-17T12:01:53Z",
    "url_soundcloud": "http://soundcloud.com/comedybangbang/best-of-2013-pt-2/#t=2:00:43",
    "tags": "Two Sides of the Coin (song),KISS (musical combination)",
    "created_at": "2017-03-17T12:01:53Z",
    "slug_soundcloud": "best-of-2013-pt-2",
    "slug_earwolf": "best-of-2013-pt-2",
    "episode_title": "",
    "episode_guests": "",
    "id_wikia": 4032,
    "holding": "false"
},

{
    "episode": "bo2013.3",
    "show": "cbb",
    "tstart": "4:05",
    "tend": "4:20",
    "instance": "I'm hiding it from you right now.",
    "bit":"The Paul Hardcastle of Suicides","elucidation":"any song reference",
    "location_type": "",
    "location_id": "",
    "updated_at": "2017-03-21T08:28:58Z",
    "url_soundcloud": "http://soundcloud.com/comedybangbang/best-of-2013-pt-3/#t=4:05",
    "tags": "The Pointer Sisters (musical combination),I'm So Excited (song)",
    "created_at": "2017-03-21T08:28:58Z",
    "slug_soundcloud": "best-of-2013-pt-3",
    "slug_earwolf": "best-of-2013-pt-3",
    "episode_title": "",
    "episode_guests": "",
    "id_wikia": 4033,
    "holding": "false"
},

{
    "episode": "bo2013.3",
    "show": "cbb",
    "tstart": "6:05",
    "tend": "6:12",
    "instance": "This is how they got together.",
    "bit":"The Paul Hardcastle of Suicides","elucidation":"any song reference",
    "location_type": "",
    "location_id": "",
    "updated_at": "2017-03-21T08:28:58Z",
    "url_soundcloud": "http://soundcloud.com/comedybangbang/best-of-2013-pt-3/#t=6:05",
    "tags": "Montell Jordan,This is How We Do It (song)",
    "created_at": "2017-03-21T08:28:58Z",
    "slug_soundcloud": "best-of-2013-pt-3",
    "slug_earwolf": "best-of-2013-pt-3",
    "episode_title": "",
    "episode_guests": "",
    "id_wikia": 4033,
    "holding": "false"
},

{
    "episode": "bo2013.3",
    "show": "cbb",
    "tstart": "1:21:37",
    "tend": "1:22:01",
    "instance": "Then you come here and the host isn't aware of what's happening at all or who the person is.",
    "bit":"You're Terrible at This","elucidation":"impromptu reviews of scott's hosting",
    "location_type": "",
    "location_id": "",
    "updated_at": "2017-03-21T08:28:58Z",
    "url_soundcloud": "http://soundcloud.com/comedybangbang/best-of-2013-pt-3/#t=1:21:37",
    "tags": "",
    "created_at": "2017-03-21T08:28:58Z",
    "slug_soundcloud": "best-of-2013-pt-3",
    "slug_earwolf": "best-of-2013-pt-3",
    "episode_title": "",
    "episode_guests": "",
    "id_wikia": 4033,
    "holding": "false"
},

{
    "episode": "bo2013.3",
    "show": "cbb",
    "tstart": "1:22:33",
    "tend": "1:22:44",
    "instance": "He was invoking the open door policy.",
    "bit":"Open Door Policy","elucidation":"cbb's open door policy is cited or blamed",
    "location_type": "",
    "location_id": "",
    "updated_at": "2017-03-21T08:28:58Z",
    "url_soundcloud": "http://soundcloud.com/comedybangbang/best-of-2013-pt-3/#t=1:22:33",
    "tags": "",
    "created_at": "2017-03-21T08:28:58Z",
    "slug_soundcloud": "best-of-2013-pt-3",
    "slug_earwolf": "best-of-2013-pt-3",
    "episode_title": "",
    "episode_guests": "",
    "id_wikia": 4033,
    "holding": "false"
},

{
    "episode": "bo2013.3",
    "show": "cbb",
    "tstart": "1:36:25",
    "tend": "1:36:50",
    "instance": "'245' is a comedy.",
    "bit":"The Paul Hardcastle of Suicides","elucidation":"any song reference",
    "location_type": "",
    "location_id": "",
    "updated_at": "2017-03-21T08:28:58Z",
    "url_soundcloud": "http://soundcloud.com/comedybangbang/best-of-2013-pt-3/#t=1:36:25",
    "tags": "1-2-3 (song),Gloria Estefan,Miami Sound Machine (musical combination)",
    "created_at": "2017-03-21T08:28:58Z",
    "slug_soundcloud": "best-of-2013-pt-3",
    "slug_earwolf": "best-of-2013-pt-3",
    "episode_title": "",
    "episode_guests": "",
    "id_wikia": 4033,
    "holding": "false"
},

{
    "episode": "bo2013.4",
    "show": "cbb",
    "tstart": "0:38",
    "tend": "1:00",
    "instance": "This is it.",
    "bit":"The Paul Hardcastle of Suicides","elucidation":"any song reference",
    "location_type": "",
    "location_id": "",
    "updated_at": "2017-03-21T11:38:29Z",
    "url_soundcloud": "http://soundcloud.com/comedybangbang/best-of-2013-pt-4/#t=0:38",
    "tags": "This is It (song),Kenny Loggins",
    "created_at": "2017-03-21T11:38:29Z",
    "slug_soundcloud": "best-of-2013-pt-4",
    "slug_earwolf": "best-of-2013-pt-4",
    "episode_title": "",
    "episode_guests": "",
    "id_wikia": 4034,
    "holding": "false"
},

{
    "episode": "bo2013.4",
    "show": "cbb",
    "tstart": "1:17",
    "tend": "1:31",
    "instance": "Can you think of any song that we know the entire --",
    "bit":"That's Also True","elucidation":"catchy thing from the first tenacious d album",
    "location_type": "",
    "location_id": "",
    "updated_at": "2017-03-21T11:38:29Z",
    "url_soundcloud": "http://soundcloud.com/comedybangbang/best-of-2013-pt-4/#t=1:17",
    "tags": "",
    "created_at": "2017-03-21T11:38:29Z",
    "slug_soundcloud": "best-of-2013-pt-4",
    "slug_earwolf": "best-of-2013-pt-4",
    "episode_title": "",
    "episode_guests": "",
    "id_wikia": 4034,
    "holding": "false"
},

{
    "episode": "bo2013.4",
    "show": "cbb",
    "tstart": "1:42",
    "tend": "1:51",
    "instance": "What are you, Jon Brion? Right?",
    "bit":"That's Also True","elucidation":"catchy thing from the first tenacious d album",
    "location_type": "",
    "location_id": "",
    "updated_at": "2017-03-21T11:38:29Z",
    "url_soundcloud": "http://soundcloud.com/comedybangbang/best-of-2013-pt-4/#t=1:42",
    "tags": "Jon Brion",
    "created_at": "2017-03-21T11:38:29Z",
    "slug_soundcloud": "best-of-2013-pt-4",
    "slug_earwolf": "best-of-2013-pt-4",
    "episode_title": "",
    "episode_guests": "",
    "id_wikia": 4034,
    "holding": "false"
},

{
    "episode": "bo2013.4",
    "show": "cbb",
    "tstart": "2:27",
    "tend": "2:37",
    "instance": "What was the point of his...",
    "bit":"The Doctor is a Woman","elucidation":"that old riddle",
    "location_type": "",
    "location_id": "",
    "updated_at": "2017-03-21T11:38:29Z",
    "url_soundcloud": "http://soundcloud.com/comedybangbang/best-of-2013-pt-4/#t=2:27",
    "tags": "",
    "created_at": "2017-03-21T11:38:29Z",
    "slug_soundcloud": "best-of-2013-pt-4",
    "slug_earwolf": "best-of-2013-pt-4",
    "episode_title": "",
    "episode_guests": "",
    "id_wikia": 4034,
    "holding": "false"
},

{
    "episode": "bo2013.4",
    "show": "cbb",
    "tstart": "7:36",
    "tend": "7:56",
    "instance": "Here's Li'l Setup.",
    "bit":"Location","elucidation":"identifiable earth location",
    "location_type": "point",
    "location_id": "6",
    "updated_at": "2017-03-21T11:38:29Z",
    "url_soundcloud": "http://soundcloud.com/comedybangbang/best-of-2013-pt-4/#t=7:36",
    "tags": "Don DiMello",
    "created_at": "2017-03-21T11:38:29Z",
    "slug_soundcloud": "best-of-2013-pt-4",
    "slug_earwolf": "best-of-2013-pt-4",
    "episode_title": "",
    "episode_guests": "",
    "id_wikia": 4034,
    "holding": "false"
},

{
    "episode": "bo2013.4",
    "show": "cbb",
    "tstart": "2:09:23",
    "tend": "2:09:35",
    "instance": "Our good friends...",
    "bit":"Cake Boss!","elucidation":"cake boss repeats 'cake boss'...cake boss.",
    "location_type": "",
    "location_id": "",
    "updated_at": "2017-03-21T11:38:29Z",
    "url_soundcloud": "http://soundcloud.com/comedybangbang/best-of-2013-pt-4/#t=2:09:23",
    "tags": "",
    "created_at": "2017-03-21T11:38:29Z",
    "slug_soundcloud": "best-of-2013-pt-4",
    "slug_earwolf": "best-of-2013-pt-4",
    "episode_title": "",
    "episode_guests": "",
    "id_wikia": 4034,
    "holding": "false"
},

{
    "episode": "bo2013.4",
    "show": "cbb",
    "tstart": "2:09:55",
    "tend": "2:10:30",
    "instance": "Out of the tree of life I just picked me a plumb.",
    "bit":"Cake Boss!","elucidation":"cake boss repeats 'cake boss'...cake boss.",
    "location_type": "",
    "location_id": "",
    "updated_at": "2017-03-21T11:38:29Z",
    "url_soundcloud": "http://soundcloud.com/comedybangbang/best-of-2013-pt-4/#t=2:09:55",
    "tags": "The Best is Yet to Come (song),Frank Sinatra",
    "created_at": "2017-03-21T11:38:29Z",
    "slug_soundcloud": "best-of-2013-pt-4",
    "slug_earwolf": "best-of-2013-pt-4",
    "episode_title": "",
    "episode_guests": "",
    "id_wikia": 4034,
    "holding": "false"
},

{
    "episode": 263,
    "show": "cbb",
    "tstart": "14:37",
    "tend": "15:14",
    "instance": "Down there by the tracks just looking for company.",
    "bit":"The Paul Hardcastle of Suicides","elucidation":"any song reference",
    "location_type": "",
    "location_id": "",
    "updated_at": "2017-03-21T14:37:25Z",
    "url_soundcloud": "http://soundcloud.com/comedybangbang/263-ben-schwartz-horatio-sanz/#t=14:37",
    "tags": "Under the Boardwalk (song),The Drifters (musical combination)",
    "created_at": "2017-03-21T14:37:25Z",
    "slug_soundcloud": "263-ben-schwartz-horatio-sanz",
    "slug_earwolf": "hollywild",
    "episode_title": "Hollywild",
    "episode_guests": "Ben Schwartz,Horatio Sanz",
    "id_wikia": 4064,
    "holding": "false"
},

{
    "episode": 263,
    "show": "cbb",
    "tstart": "15:10",
    "tend": "15:14",
    "instance": "It makes me smile when we sing.",
    "bit":"Rudimentary Drum Solos","elucidation":"scott performs a drum solo",
    "location_type": "",
    "location_id": "",
    "updated_at": "2017-03-21T14:37:25Z",
    "url_soundcloud": "http://soundcloud.com/comedybangbang/263-ben-schwartz-horatio-sanz/#t=15:10",
    "tags": "",
    "created_at": "2017-03-21T14:37:25Z",
    "slug_soundcloud": "263-ben-schwartz-horatio-sanz",
    "slug_earwolf": "hollywild",
    "episode_title": "Hollywild",
    "episode_guests": "Ben Schwartz,Horatio Sanz",
    "id_wikia": 4064,
    "holding": "false"
},

{
    "episode": 263,
    "show": "cbb",
    "tstart": "20:24",
    "tend": "20:50",
    "instance": "You make me gh-gh-gh--",
    "bit":"The Paul Hardcastle of Suicides","elucidation":"any song reference",
    "location_type": "",
    "location_id": "",
    "updated_at": "2017-03-21T14:37:25Z",
    "url_soundcloud": "http://soundcloud.com/comedybangbang/263-ben-schwartz-horatio-sanz/#t=20:24",
    "tags": "The Way You Make Me Feel (song),Michael Jackson",
    "created_at": "2017-03-21T14:37:25Z",
    "slug_soundcloud": "263-ben-schwartz-horatio-sanz",
    "slug_earwolf": "hollywild",
    "episode_title": "Hollywild",
    "episode_guests": "Ben Schwartz,Horatio Sanz",
    "id_wikia": 4064,
    "holding": "false"
},

{
    "episode": 263,
    "show": "cbb",
    "tstart": "23:36",
    "tend": "23:56",
    "instance": "You know what? You can. Hit me.",
    "bit":"The Paul Hardcastle of Suicides","elucidation":"any song reference",
    "location_type": "",
    "location_id": "",
    "updated_at": "2017-03-21T14:37:25Z",
    "url_soundcloud": "http://soundcloud.com/comedybangbang/263-ben-schwartz-horatio-sanz/#t=23:36",
    "tags": "Under the Boardwalk (song),The Drifters (musical combination)",
    "created_at": "2017-03-21T14:37:25Z",
    "slug_soundcloud": "263-ben-schwartz-horatio-sanz",
    "slug_earwolf": "hollywild",
    "episode_title": "Hollywild",
    "episode_guests": "Ben Schwartz,Horatio Sanz",
    "id_wikia": 4064,
    "holding": "false"
},

{
    "episode": 263,
    "show": "cbb",
    "tstart": "25:55",
    "tend": "26:10",
    "instance": "Everything about it is appealing.",
    "bit":"The Paul Hardcastle of Suicides","elucidation":"any song reference",
    "location_type": "",
    "location_id": "",
    "updated_at": "2017-03-21T14:37:25Z",
    "url_soundcloud": "http://soundcloud.com/comedybangbang/263-ben-schwartz-horatio-sanz/#t=25:55",
    "tags": "There's No Business Like Show Business (song),Irving Berlin,Ethel Merman",
    "created_at": "2017-03-21T14:37:25Z",
    "slug_soundcloud": "263-ben-schwartz-horatio-sanz",
    "slug_earwolf": "hollywild",
    "episode_title": "Hollywild",
    "episode_guests": "Ben Schwartz,Horatio Sanz",
    "id_wikia": 4064,
    "holding": "false"
},

{
    "episode": 263,
    "show": "cbb",
    "tstart": "44:22",
    "tend": "44:39",
    "instance": "I know that one about cotton.",
    "bit":"The Paul Hardcastle of Suicides","elucidation":"any song reference",
    "location_type": "",
    "location_id": "",
    "updated_at": "2017-03-21T14:37:25Z",
    "url_soundcloud": "http://soundcloud.com/comedybangbang/263-ben-schwartz-horatio-sanz/#t=44:22",
    "tags": "Tell it Like it Is (song),Aaron Neville",
    "created_at": "2017-03-21T14:37:25Z",
    "slug_soundcloud": "263-ben-schwartz-horatio-sanz",
    "slug_earwolf": "hollywild",
    "episode_title": "Hollywild",
    "episode_guests": "Ben Schwartz,Horatio Sanz",
    "id_wikia": 4064,
    "holding": "false"
},

{
    "episode": 263,
    "show": "cbb",
    "tstart": "44:38",
    "tend": "44:59",
    "instance": "Coco does a crazy good Aaron Neville.",
    "bit":"The Paul Hardcastle of Suicides","elucidation":"any song reference",
    "location_type": "",
    "location_id": "",
    "updated_at": "2017-03-21T14:37:25Z",
    "url_soundcloud": "http://soundcloud.com/comedybangbang/263-ben-schwartz-horatio-sanz/#t=44:38",
    "tags": "Don't Know Much (song),Linda Ronstadt,Aaron Neville",
    "created_at": "2017-03-21T14:37:25Z",
    "slug_soundcloud": "263-ben-schwartz-horatio-sanz",
    "slug_earwolf": "hollywild",
    "episode_title": "Hollywild",
    "episode_guests": "Ben Schwartz,Horatio Sanz",
    "id_wikia": 4064,
    "holding": "false"
},

{
    "episode": 263,
    "show": "cbb",
    "tstart": "46:52",
    "tend": "47:19",
    "instance": "We have one of our favorite guests.",
    "bit":"The Paul Hardcastle of Suicides","elucidation":"any song reference",
    "location_type": "",
    "location_id": "",
    "updated_at": "2017-03-21T14:37:25Z",
    "url_soundcloud": "http://soundcloud.com/comedybangbang/263-ben-schwartz-horatio-sanz/#t=46:52",
    "tags": "Bennie and the Jets (song),Elton John,Bernie Taupin",
    "created_at": "2017-03-21T14:37:25Z",
    "slug_soundcloud": "263-ben-schwartz-horatio-sanz",
    "slug_earwolf": "hollywild",
    "episode_title": "Hollywild",
    "episode_guests": "Ben Schwartz,Horatio Sanz",
    "id_wikia": 4064,
    "holding": "false"
},

{
    "episode": 263,
    "show": "cbb",
    "tstart": "48:02",
    "tend": "48:13",
    "instance": "And then they asked you to shake it all about.",
    "bit":"The Paul Hardcastle of Suicides","elucidation":"any song reference",
    "location_type": "",
    "location_id": "",
    "updated_at": "2017-03-21T14:37:25Z",
    "url_soundcloud": "http://soundcloud.com/comedybangbang/263-ben-schwartz-horatio-sanz/#t=48:02",
    "tags": "Hokey Pokey (song)",
    "created_at": "2017-03-21T14:37:25Z",
    "slug_soundcloud": "263-ben-schwartz-horatio-sanz",
    "slug_earwolf": "hollywild",
    "episode_title": "Hollywild",
    "episode_guests": "Ben Schwartz,Horatio Sanz",
    "id_wikia": 4064,
    "holding": "false"
},

{
    "episode": 263,
    "show": "cbb",
    "tstart": "51:08",
    "tend": "51:19",
    "instance": "I mean - who would put 'pussy eater' on their arm if they could help it?",
    "bit":"Location","elucidation":"identifiable earth location",
    "location_type": "poly",
    "location_id": "407",
    "updated_at": "2017-03-21T14:37:25Z",
    "url_soundcloud": "http://soundcloud.com/comedybangbang/263-ben-schwartz-horatio-sanz/#t=51:08",
    "tags": "Coco Marx",
    "created_at": "2017-03-21T14:37:25Z",
    "slug_soundcloud": "263-ben-schwartz-horatio-sanz",
    "slug_earwolf": "hollywild",
    "episode_title": "Hollywild",
    "episode_guests": "Ben Schwartz,Horatio Sanz",
    "id_wikia": 4064,
    "holding": "false"
},

{
    "episode": 263,
    "show": "cbb",
    "tstart": "57:09",
    "tend": "57:32",
    "instance": "I got a job I gotta go to - I must be going.",
    "bit":"The Paul Hardcastle of Suicides","elucidation":"any song reference",
    "location_type": "",
    "location_id": "",
    "updated_at": "2017-03-21T14:37:25Z",
    "url_soundcloud": "http://soundcloud.com/comedybangbang/263-ben-schwartz-horatio-sanz/#t=57:09",
    "tags": "Coco Marx,Hello, I Must Be Going (song),Harry Ruby,Bert Kalmar",
    "created_at": "2017-03-21T14:37:25Z",
    "slug_soundcloud": "263-ben-schwartz-horatio-sanz",
    "slug_earwolf": "hollywild",
    "episode_title": "Hollywild",
    "episode_guests": "Ben Schwartz,Horatio Sanz",
    "id_wikia": 4064,
    "holding": "false"
},

{
    "episode": 263,
    "show": "cbb",
    "tstart": "57:38",
    "tend": "57:55",
    "instance": "Sometimes it rains down in Africa.",
    "bit":"The Paul Hardcastle of Suicides","elucidation":"any song reference",
    "location_type": "",
    "location_id": "",
    "updated_at": "2017-03-21T14:37:25Z",
    "url_soundcloud": "http://soundcloud.com/comedybangbang/263-ben-schwartz-horatio-sanz/#t=57:38",
    "tags": "Coco Marx,Africa (song),Toto (musical combination)",
    "created_at": "2017-03-21T14:37:25Z",
    "slug_soundcloud": "263-ben-schwartz-horatio-sanz",
    "slug_earwolf": "hollywild",
    "episode_title": "Hollywild",
    "episode_guests": "Ben Schwartz,Horatio Sanz",
    "id_wikia": 4064,
    "holding": "false"
},

{
    "episode": 263,
    "show": "cbb",
    "tstart": "1:02:35",
    "tend": "1:02:48",
    "instance": "What do you call a chimpanzee with amn--",
    "bit":"Too Soon","elucidation":"someone uses, misuses, or riffs on 'too soon'",
    "location_type": "",
    "location_id": "",
    "updated_at": "2017-03-21T14:37:25Z",
    "url_soundcloud": "http://soundcloud.com/comedybangbang/263-ben-schwartz-horatio-sanz/#t=1:02:35",
    "tags": "",
    "created_at": "2017-03-21T14:37:25Z",
    "slug_soundcloud": "263-ben-schwartz-horatio-sanz",
    "slug_earwolf": "hollywild",
    "episode_title": "Hollywild",
    "episode_guests": "Ben Schwartz,Horatio Sanz",
    "id_wikia": 4064,
    "holding": "false"
},

{
    "episode": 263,
    "show": "cbb",
    "tstart": "1:06:57",
    "tend": "1:07:13",
    "instance": "That's cheating, kids.",
    "bit":"Eatin' Ain't Cheatin'","elucidation":"someone does a bill clinton",
    "location_type": "",
    "location_id": "",
    "updated_at": "2017-03-21T14:37:25Z",
    "url_soundcloud": "http://soundcloud.com/comedybangbang/263-ben-schwartz-horatio-sanz/#t=1:06:57",
    "tags": "",
    "created_at": "2017-03-21T14:37:25Z",
    "slug_soundcloud": "263-ben-schwartz-horatio-sanz",
    "slug_earwolf": "hollywild",
    "episode_title": "Hollywild",
    "episode_guests": "Ben Schwartz,Horatio Sanz",
    "id_wikia": 4064,
    "holding": "false"
},

{
    "episode": 263,
    "show": "cbb",
    "tstart": "1:10:47",
    "tend": "1:11:01",
    "instance": "And then they're dead - that's why they're lying down.",
    "bit":"The Paul Hardcastle of Suicides","elucidation":"any song reference",
    "location_type": "",
    "location_id": "",
    "updated_at": "2017-03-21T14:37:25Z",
    "url_soundcloud": "http://soundcloud.com/comedybangbang/263-ben-schwartz-horatio-sanz/#t=1:10:47",
    "tags": "Nobody Knows the Trouble I've Seen (song),Coco Marx",
    "created_at": "2017-03-21T14:37:25Z",
    "slug_soundcloud": "263-ben-schwartz-horatio-sanz",
    "slug_earwolf": "hollywild",
    "episode_title": "Hollywild",
    "episode_guests": "Ben Schwartz,Horatio Sanz",
    "id_wikia": 4064,
    "holding": "false"
},

{
    "episode": 263,
    "show": "cbb",
    "tstart": "1:15:12",
    "tend": "1:15:47",
    "instance": "Here we go - biggest thing for me.",
    "bit":"The Paul Hardcastle of Suicides","elucidation":"any song reference",
    "location_type": "",
    "location_id": "",
    "updated_at": "2017-03-21T14:37:25Z",
    "url_soundcloud": "http://soundcloud.com/comedybangbang/263-ben-schwartz-horatio-sanz/#t=1:15:12",
    "tags": "Here I Go Again (song),Whitesnake (musical combination),Coco Marx",
    "created_at": "2017-03-21T14:37:25Z",
    "slug_soundcloud": "263-ben-schwartz-horatio-sanz",
    "slug_earwolf": "hollywild",
    "episode_title": "Hollywild",
    "episode_guests": "Ben Schwartz,Horatio Sanz",
    "id_wikia": 4064,
    "holding": "false"
},

{
    "episode": 263,
    "show": "cbb",
    "tstart": "1:19:48",
    "tend": "1:20:00",
    "instance": "'Texter' is a 'Dexter' ripoff.",
    "bit":"Texter","elucidation":"dexter when he texts",
    "location_type": "",
    "location_id": "",
    "updated_at": "2017-03-21T14:37:25Z",
    "url_soundcloud": "http://soundcloud.com/comedybangbang/263-ben-schwartz-horatio-sanz/#t=1:19:48",
    "tags": "",
    "created_at": "2017-03-21T14:37:25Z",
    "slug_soundcloud": "263-ben-schwartz-horatio-sanz",
    "slug_earwolf": "hollywild",
    "episode_title": "Hollywild",
    "episode_guests": "Ben Schwartz,Horatio Sanz",
    "id_wikia": 4064,
    "holding": "false"
},

{
    "episode": 263,
    "show": "cbb",
    "tstart": "1:20:34",
    "tend": "1:20:44",
    "instance": "We are...",
    "bit":"The Paul Hardcastle of Suicides","elucidation":"any song reference",
    "location_type": "",
    "location_id": "",
    "updated_at": "2017-03-21T14:37:25Z",
    "url_soundcloud": "http://soundcloud.com/comedybangbang/263-ben-schwartz-horatio-sanz/#t=1:20:34",
    "tags": "Youth of the Nation (song),P.O.D. (musical combination)",
    "created_at": "2017-03-21T14:37:25Z",
    "slug_soundcloud": "263-ben-schwartz-horatio-sanz",
    "slug_earwolf": "hollywild",
    "episode_title": "Hollywild",
    "episode_guests": "Ben Schwartz,Horatio Sanz",
    "id_wikia": 4064,
    "holding": "false"
},

{
    "episode": 263,
    "show": "cbb",
    "tstart": "1:21:10",
    "tend": "1:21:16",
    "instance": "So come out and see us.",
    "bit":"The Paul Hardcastle of Suicides","elucidation":"any song reference",
    "location_type": "",
    "location_id": "",
    "updated_at": "2017-03-21T14:37:25Z",
    "url_soundcloud": "http://soundcloud.com/comedybangbang/263-ben-schwartz-horatio-sanz/#t=1:21:10",
    "tags": "Come Up and See Me Sometime (song)",
    "created_at": "2017-03-21T14:37:25Z",
    "slug_soundcloud": "263-ben-schwartz-horatio-sanz",
    "slug_earwolf": "hollywild",
    "episode_title": "Hollywild",
    "episode_guests": "Ben Schwartz,Horatio Sanz",
    "id_wikia": 4064,
    "holding": "false"
},

{
    "episode": 264,
    "show": "cbb",
    "tstart": "2:24",
    "tend": "2:39",
    "instance": "Kroll Show/Kroll Show",
    "bit":"The Paul Hardcastle of Suicides","elucidation":"any song reference",
    "location_type": "",
    "location_id": "",
    "updated_at": "2017-03-22T09:50:57Z",
    "url_soundcloud": "http://soundcloud.com/comedybangbang/264-nick-kroll-jenny-slate/#t=2:24",
    "tags": "Adam Ant,Goody Two Shoes (song)",
    "created_at": "2017-03-22T09:50:57Z",
    "slug_soundcloud": "264-nick-kroll-jenny-slate",
    "slug_earwolf": "creating-a-krolliverse",
    "episode_title": "Creating A Krolliverse",
    "episode_guests": "Nick Kroll,Jenny Slate",
    "id_wikia": 4093,
    "holding": "false"
},

{
    "episode": 264,
    "show": "cbb",
    "tstart": "46:46",
    "tend": "47:10",
    "instance": "In order to get him to, like, go to bed at night we listen to the sounds of milk being poured.",
    "bit":"The Paul Hardcastle of Suicides","elucidation":"any song reference",
    "location_type": "",
    "location_id": "",
    "updated_at": "2017-03-22T09:50:57Z",
    "url_soundcloud": "http://soundcloud.com/comedybangbang/264-nick-kroll-jenny-slate/#t=46:46",
    "tags": "Kesha,TiK ToK (song),Pretty Liz,C-Czar",
    "created_at": "2017-03-22T09:50:57Z",
    "slug_soundcloud": "264-nick-kroll-jenny-slate",
    "slug_earwolf": "creating-a-krolliverse",
    "episode_title": "Creating A Krolliverse",
    "episode_guests": "Nick Kroll,Jenny Slate",
    "id_wikia": 4093,
    "holding": "false"
},

{
    "episode": 264,
    "show": "cbb",
    "tstart": "47:27",
    "tend": "47:57",
    "instance": "Either we've known each other for, like, ever or we met, like, four years ago.",
    "bit":"Location","elucidation":"identifiable earth location",
    "location_type": "poly",
    "location_id": "408",
    "updated_at": "2017-03-22T09:50:57Z",
    "url_soundcloud": "http://soundcloud.com/comedybangbang/264-nick-kroll-jenny-slate/#t=47:27",
    "tags": "Pretty Liz,C-Czar",
    "created_at": "2017-03-22T09:50:57Z",
    "slug_soundcloud": "264-nick-kroll-jenny-slate",
    "slug_earwolf": "creating-a-krolliverse",
    "episode_title": "Creating A Krolliverse",
    "episode_guests": "Nick Kroll,Jenny Slate",
    "id_wikia": 4093,
    "holding": "false"
},

{
    "episode": 264,
    "show": "cbb",
    "tstart": "49:18",
    "tend": "49:31",
    "instance": "He's a toilet baby.",
    "bit":"Location","elucidation":"identifiable earth location",
    "location_type": "poly",
    "location_id": "189",
    "updated_at": "2017-03-22T09:50:57Z",
    "url_soundcloud": "http://soundcloud.com/comedybangbang/264-nick-kroll-jenny-slate/#t=49:18",
    "tags": "Pretty Liz,C-Czar",
    "created_at": "2017-03-22T09:50:57Z",
    "slug_soundcloud": "264-nick-kroll-jenny-slate",
    "slug_earwolf": "creating-a-krolliverse",
    "episode_title": "Creating A Krolliverse",
    "episode_guests": "Nick Kroll,Jenny Slate",
    "id_wikia": 4093,
    "holding": "false"
},

{
    "episode": 265,
    "show": "cbb",
    "tstart": "46:45",
    "tend": "46:58",
    "instance": "Souped up - all special - all tricked out.",
    "bit":"Too Soon","elucidation":"someone uses, misuses, or riffs on 'too soon'",
    "location_type": "",
    "location_id": "",
    "updated_at": "2017-03-22T13:34:58Z",
    "url_soundcloud": "http://soundcloud.com/comedybangbang/265-live-from-riot-la-paul-f/#t=46:45",
    "tags": "Traci Rearden,J.W. Stillwater",
    "created_at": "2017-03-22T13:34:58Z",
    "slug_soundcloud": "265-live-from-riot-la-paul-f",
    "slug_earwolf": "live-from-riot-la-2",
    "episode_title": "LIVE from RIOT LA",
    "episode_guests": "Paul F. Tompkins,Lauren Lapkus,Harris Wittels",
    "id_wikia": 4106,
    "holding": "false"
},

{
    "episode": 265,
    "show": "cbb",
    "tstart": "1:09:09",
    "tend": "1:09:31",
    "instance": "'Overruled - snap' on the front/'thats gotta hurt' on the back",
    "bit":"Rearden Ts","elucidation":"someone (usually traci rearden) proposes a t-shirt design",
    "location_type": "",
    "location_id": "",
    "updated_at": "2017-03-22T13:34:58Z",
    "url_soundcloud": "http://soundcloud.com/comedybangbang/265-live-from-riot-la-paul-f/#t=1:09:09",
    "tags": "Traci Rearden,J.W. Stillwater",
    "created_at": "2017-03-22T13:34:58Z",
    "slug_soundcloud": "265-live-from-riot-la-paul-f",
    "slug_earwolf": "live-from-riot-la-2",
    "episode_title": "LIVE from RIOT LA",
    "episode_guests": "Paul F. Tompkins,Lauren Lapkus,Harris Wittels",
    "id_wikia": 4106,
    "holding": "false"
},

{
    "episode": 265,
    "show": "cbb",
    "tstart": "1:11:33",
    "tend": "1:11:39",
    "instance": "'Hot' on the front/'Saucerman' on the back",
    "bit":"Rearden Ts","elucidation":"someone (usually traci rearden) proposes a t-shirt design",
    "location_type": "",
    "location_id": "",
    "updated_at": "2017-03-22T13:34:58Z",
    "url_soundcloud": "http://soundcloud.com/comedybangbang/265-live-from-riot-la-paul-f/#t=1:11:33",
    "tags": "Traci Rearden,J.W. Stillwater",
    "created_at": "2017-03-22T13:34:58Z",
    "slug_soundcloud": "265-live-from-riot-la-paul-f",
    "slug_earwolf": "live-from-riot-la-2",
    "episode_title": "LIVE from RIOT LA",
    "episode_guests": "Paul F. Tompkins,Lauren Lapkus,Harris Wittels",
    "id_wikia": 4106,
    "holding": "false"
},

{
    "episode": 265,
    "show": "cbb",
    "tstart": "1:11:55",
    "tend": "1:12:04",
    "instance": "'Bell Biv' on the front/'Devoe' on the back",
    "bit":"Rearden Ts","elucidation":"someone (usually traci rearden) proposes a t-shirt design",
    "location_type": "",
    "location_id": "",
    "updated_at": "2017-03-22T13:34:58Z",
    "url_soundcloud": "http://soundcloud.com/comedybangbang/265-live-from-riot-la-paul-f/#t=1:11:55",
    "tags": "Traci Rearden,J.W. Stillwater,Bell Biv DeVoe (musical combination)",
    "created_at": "2017-03-22T13:34:58Z",
    "slug_soundcloud": "265-live-from-riot-la-paul-f",
    "slug_earwolf": "live-from-riot-la-2",
    "episode_title": "LIVE from RIOT LA",
    "episode_guests": "Paul F. Tompkins,Lauren Lapkus,Harris Wittels",
    "id_wikia": 4106,
    "holding": "false"
},

{
    "episode": 265,
    "show": "cbb",
    "tstart": "1:14:03",
    "tend": "1:14:30",
    "instance": "'Snapping Justice' on the front/'thats gotta hurt' on the back",
    "bit":"Rearden Ts","elucidation":"someone (usually traci rearden) proposes a t-shirt design",
    "location_type": "",
    "location_id": "",
    "updated_at": "2017-03-22T13:34:58Z",
    "url_soundcloud": "http://soundcloud.com/comedybangbang/265-live-from-riot-la-paul-f/#t=1:14:03",
    "tags": "Traci Rearden,J.W. Stillwater",
    "created_at": "2017-03-22T13:34:58Z",
    "slug_soundcloud": "265-live-from-riot-la-paul-f",
    "slug_earwolf": "live-from-riot-la-2",
    "episode_title": "LIVE from RIOT LA",
    "episode_guests": "Paul F. Tompkins,Lauren Lapkus,Harris Wittels",
    "id_wikia": 4106,
    "holding": "false"
},

{
    "episode": 265,
    "show": "cbb",
    "tstart": "1:15:25",
    "tend": "1:15:38",
    "instance": "'Hubba' on the front/'Hubba' on the back",
    "bit":"Rearden Ts","elucidation":"someone (usually traci rearden) proposes a t-shirt design",
    "location_type": "",
    "location_id": "",
    "updated_at": "2017-03-22T13:34:58Z",
    "url_soundcloud": "http://soundcloud.com/comedybangbang/265-live-from-riot-la-paul-f/#t=1:15:25",
    "tags": "Traci Rearden,J.W. Stillwater",
    "created_at": "2017-03-22T13:34:58Z",
    "slug_soundcloud": "265-live-from-riot-la-paul-f",
    "slug_earwolf": "live-from-riot-la-2",
    "episode_title": "LIVE from RIOT LA",
    "episode_guests": "Paul F. Tompkins,Lauren Lapkus,Harris Wittels",
    "id_wikia": 4106,
    "holding": "false"
},

{
    "episode": 265,
    "show": "cbb",
    "tstart": "1:16:18",
    "tend": "1:16:34",
    "instance": "They play it when you run the mile at school.",
    "bit":"Rearden Ts","elucidation":"someone (usually traci rearden) proposes a t-shirt design",
    "location_type": "",
    "location_id": "",
    "updated_at": "2017-03-22T13:34:58Z",
    "url_soundcloud": "http://soundcloud.com/comedybangbang/265-live-from-riot-la-paul-f/#t=1:16:18",
    "tags": "Chariots of Fire (song),Chariots of Fire (film),Vangelis,Traci Rearden,J.W. Stillwater",
    "created_at": "2017-03-22T13:34:58Z",
    "slug_soundcloud": "265-live-from-riot-la-paul-f",
    "slug_earwolf": "live-from-riot-la-2",
    "episode_title": "LIVE from RIOT LA",
    "episode_guests": "Paul F. Tompkins,Lauren Lapkus,Harris Wittels",
    "id_wikia": 4106,
    "holding": "false"
}]