[{
	"episode": 452,
	"show": "cbb",
	"tstart": "1:57",
	"tend": "2:21",
	"instance": "I'm unclear on whether I'm the host or not.",
	"bit":"Good Advice",
	"elucidation":"a guest performs before they're announced",
	"location_type": "",
	"location_id": "",
	"updated_at": "2016-10-25T07:55:05Z",
	"url_soundcloud": "https://soundcloud.com/comedybangbang/452-weird-al-yankovic-claudia-odoherty-jessica-mckenna/#t=1:57",
	"tags": "",
	"created_at": "2016-10-25T07:55:05Z",
	"slug_soundcloud": "452-weird-al-yankovic-claudia-odoherty-jessica-mckenna",
	"slug_earwolf": "pow-pow-power-wheels",
	"episode_title": "Pow! Pow! Power Wheels!",
	"episode_guests": "Weird Al Yankovic, Claudia O'Doherty, Jessica McKenna",
	"id_wikia": null,
	"holding": "false"
},

{
	"episode": 452,
	"show": "cbb",
	"tstart": "12:22",
	"tend": "12:34",
	"instance": "Wait, are you asking me for a ride?",
	"bit":"Location",
	"elucidation":"identifiable earth location",
	"location_type": "poly",
	"location_id": "372",
	"updated_at": "2016-10-25T07:55:05Z",
	"url_soundcloud": "https://soundcloud.com/comedybangbang/452-weird-al-yankovic-claudia-odoherty-jessica-mckenna/#t=12:22",
	"tags": "",
	"created_at": "2016-10-25T07:55:05Z",
	"slug_soundcloud": "452-weird-al-yankovic-claudia-odoherty-jessica-mckenna",
	"slug_earwolf": "pow-pow-power-wheels",
	"episode_title": "Pow! Pow! Power Wheels!",
	"episode_guests": "Weird Al Yankovic, Claudia O'Doherty, Jessica McKenna",
	"id_wikia": null,
	"holding": "false"
},

{
	"episode": 452,
	"show": "cbb",
	"tstart": "41:15",
	"tend": "41:33",
	"instance": "By the way, how many lbs are you at?",
	"bit":"What's Your Address?",
	"elucidation":"scott asks an inappropriately personal question",
	"location_type": "",
	"location_id": "",
	"updated_at": "2016-10-25T07:55:05Z",
	"url_soundcloud": "https://soundcloud.com/comedybangbang/452-weird-al-yankovic-claudia-odoherty-jessica-mckenna/#t=41:15",
	"tags": "Beth",
	"created_at": "2016-10-25T07:55:05Z",
	"slug_soundcloud": "452-weird-al-yankovic-claudia-odoherty-jessica-mckenna",
	"slug_earwolf": "pow-pow-power-wheels",
	"episode_title": "Pow! Pow! Power Wheels!",
	"episode_guests": "Weird Al Yankovic, Claudia O'Doherty, Jessica McKenna",
	"id_wikia": null,
	"holding": "false"
},

{
	"episode": 452,
	"show": "cbb",
	"tstart": "42:48",
	"tend": "43:09",
	"instance": "The ghost of your food.",
	"bit":"The Ghost of a Burger",
	"elucidation":"a turd",
	"location_type": "",
	"location_id": "",
	"updated_at": "2016-10-25T07:55:05Z",
	"url_soundcloud": "https://soundcloud.com/comedybangbang/452-weird-al-yankovic-claudia-odoherty-jessica-mckenna/#t=42:48",
	"tags": "Beth",
	"created_at": "2016-10-25T07:55:05Z",
	"slug_soundcloud": "452-weird-al-yankovic-claudia-odoherty-jessica-mckenna",
	"slug_earwolf": "pow-pow-power-wheels",
	"episode_title": "Pow! Pow! Power Wheels!",
	"episode_guests": "Weird Al Yankovic, Claudia O'Doherty, Jessica McKenna",
	"id_wikia": null,
	"holding": "false"
},

{
	"episode": 452,
	"show": "cbb",
	"tstart": "44:15",
	"tend": "44:31",
	"instance": "So the carpet matches the drapes.",
	"bit":"What's Your Address?",
	"elucidation":"scott asks an inappropriately personal question",
	"location_type": "",
	"location_id": "",
	"updated_at": "2016-10-25T07:55:05Z",
	"url_soundcloud": "https://soundcloud.com/comedybangbang/452-weird-al-yankovic-claudia-odoherty-jessica-mckenna/#t=44:15",
	"tags": "Beth",
	"created_at": "2016-10-25T07:55:05Z",
	"slug_soundcloud": "452-weird-al-yankovic-claudia-odoherty-jessica-mckenna",
	"slug_earwolf": "pow-pow-power-wheels",
	"episode_title": "Pow! Pow! Power Wheels!",
	"episode_guests": "Weird Al Yankovic, Claudia O'Doherty, Jessica McKenna",
	"id_wikia": null,
	"holding": "false"
},

{
	"episode": 452,
	"show": "cbb",
	"tstart": "48:30",
	"tend": "48:35",
	"instance": "Oh yeah? She your favorite?",
	"bit":"How Many?",
	"elucidation":"a pimping subclass: somebody asks for a list of things",
	"location_type": "",
	"location_id": "",
	"updated_at": "2016-10-25T07:55:05Z",
	"url_soundcloud": "https://soundcloud.com/comedybangbang/452-weird-al-yankovic-claudia-odoherty-jessica-mckenna/#t=48:30",
	"tags": "Beth,Saturday Night Live (TV)",
	"created_at": "2016-10-25T07:55:05Z",
	"slug_soundcloud": "452-weird-al-yankovic-claudia-odoherty-jessica-mckenna",
	"slug_earwolf": "pow-pow-power-wheels",
	"episode_title": "Pow! Pow! Power Wheels!",
	"episode_guests": "Weird Al Yankovic, Claudia O'Doherty, Jessica McKenna",
	"id_wikia": null,
	"holding": "false"
},

{
	"episode": 452,
	"show": "cbb",
	"tstart": "56:18",
	"tend": "56:39",
	"instance": "Breakfast at Chili's or breakfast of chili?",
	"bit":"Location",
	"elucidation":"identifiable earth location",
	"location_type": "point",
	"location_id": "721",
	"updated_at": "2016-10-25T07:55:05Z",
	"url_soundcloud": "https://soundcloud.com/comedybangbang/452-weird-al-yankovic-claudia-odoherty-jessica-mckenna/#t=56:18",
	"tags": "",
	"created_at": "2016-10-25T07:55:05Z",
	"slug_soundcloud": "452-weird-al-yankovic-claudia-odoherty-jessica-mckenna",
	"slug_earwolf": "pow-pow-power-wheels",
	"episode_title": "Pow! Pow! Power Wheels!",
	"episode_guests": "Weird Al Yankovic, Claudia O'Doherty, Jessica McKenna",
	"id_wikia": null,
	"holding": "false"
},

{
	"episode": 452,
	"show": "cbb",
	"tstart": "1:00:36",
	"tend": "1:00:46",
	"instance": "To have Tupac teaching you things.",
	"bit":"That is the Dream",
	"elucidation":"scott seems jealous or just commendatory",
	"location_type": "",
	"location_id": "",
	"updated_at": "2016-10-25T07:55:05Z",
	"url_soundcloud": "https://soundcloud.com/comedybangbang/452-weird-al-yankovic-claudia-odoherty-jessica-mckenna/#t=1:00:36",
	"tags": "",
	"created_at": "2016-10-25T07:55:05Z",
	"slug_soundcloud": "452-weird-al-yankovic-claudia-odoherty-jessica-mckenna",
	"slug_earwolf": "pow-pow-power-wheels",
	"episode_title": "Pow! Pow! Power Wheels!",
	"episode_guests": "Weird Al Yankovic, Claudia O'Doherty, Jessica McKenna",
	"id_wikia": null,
	"holding": "false"
},

{
	"episode": 452,
	"show": "cbb",
	"tstart": "1:10:18",
	"tend": "1:10:25",
	"instance": "Two thousand pounds of people.",
	"bit":"Group Coupon",
	"elucidation":"scott articulates obvious data (acronyms, abbreviations, etc.)",
	"location_type": "",
	"location_id": "",
	"updated_at": "2016-10-25T07:55:05Z",
	"url_soundcloud": "https://soundcloud.com/comedybangbang/452-weird-al-yankovic-claudia-odoherty-jessica-mckenna/#t=1:10:18",
	"tags": "",
	"created_at": "2016-10-25T07:55:05Z",
	"slug_soundcloud": "452-weird-al-yankovic-claudia-odoherty-jessica-mckenna",
	"slug_earwolf": "pow-pow-power-wheels",
	"episode_title": "Pow! Pow! Power Wheels!",
	"episode_guests": "Weird Al Yankovic, Claudia O'Doherty, Jessica McKenna",
	"id_wikia": null,
	"holding": "false"
}]